.kubetemplate.sample
MANIFEST.in
README.md
setup.py
kubetemplate/__init__.py
kubetemplate/command.py
kubetemplate/compile.py
kubetemplate/helpers.py
kubetemplate/utils.py
kubetemplate.egg-info/PKG-INFO
kubetemplate.egg-info/SOURCES.txt
kubetemplate.egg-info/dependency_links.txt
kubetemplate.egg-info/entry_points.txt
kubetemplate.egg-info/requires.txt
kubetemplate.egg-info/top_level.txt