Metadata-Version: 1.0
Name: kubetemplate
Version: 0.0.1
Summary: Kubernetes specific helpers and Jinja templating
Home-page: https://github.com/hasura/kubetemplate
Author: Akshaya Acharya
Author-email: akshaya@hasura.io
License: MIT
Keywords: kubernetes template templating jinja pangaea
Platform: UNKNOWN
